<ns0:record xmlns:dc="http://purl.org/dc/elements/1.1/" xmlns:ns0="http://www.openarchives.org/OAI/2.0/" xmlns:ns2="http://www.openarchives.org/ore/terms/" xmlns:ns3="http://www.europeana.eu/schemas/edm/" xmlns:ns5="http://purl.org/dc/terms/" xmlns:ns6="http://rdfs.org/sioc/services#" xmlns:ns7="http://www.w3.org/2004/02/skos/core#" xmlns:ns8="http://www.w3.org/2002/07/owl#" xmlns:ns9="http://rdvocab.info/ElementsGr2/" xmlns:rdf="http://www.w3.org/1999/02/22-rdf-syntax-ns#">
      <ns0:header>
        <ns0:identifier>https://id.rijksmuseum.nl/200107963</ns0:identifier>
        <ns0:datestamp>2026-06-08T00:16:56Z</ns0:datestamp>
        <ns0:setSpec>260212</ns0:setSpec>
        <ns0:setSpec>260214</ns0:setSpec>
        <ns0:setSpec>260239</ns0:setSpec>
        <ns0:setSpec>261208</ns0:setSpec>
        <ns0:setSpec>26121</ns0:setSpec>
        <ns0:setSpec>260251</ns0:setSpec>
      </ns0:header>
      <ns0:metadata>
        <rdf:RDF>
          <ns2:Aggregation rdf:about="https://id.rijksmuseum.nl/200107963#aggregation">
            <ns3:aggregatedCHO>
              <ns3:ProvidedCHO rdf:about="https://id.rijksmuseum.nl/200107963">
                <dc:creator rdf:resource="https://id.rijksmuseum.nl/2101346" />
                <dc:description xml:lang="en">Saenredam specialized in architectural painting. He studied buildings closely, making detailed drawings of them, which he then reworked into paintings. Here he chose a vantage point from behind an arch, which creates a second framing element. Our gaze is automatically drawn upwards to the old organ, which has a painted scene of the Resurrection of Christ. This is a remnant of the by-then long-abolished Catholic
decoration.</dc:description>
                <dc:description xml:lang="nl">Saenredam was een specialist in het schilderen van architectuur. Hij bestudeerde de bouwwerken en maakte gedetailleerde tekeningen, die hij uitwerkte tot schilderijen. Hier koos hij een gezichtspunt van achter een boog, waardoor een tweede omlijsting ontstaat. Daardoor gaat de blik vanzelf omhoog naar het oude orgel, dat beschilderd is met de opstanding van Christus: een overblijfsel van destijds allang afgeschafte katholieke versieringen.</dc:description>
                <dc:identifier>SK-A-359</dc:identifier>
                <dc:relation rdf:resource="https://id.rijksmuseum.nl/20066820" />
                <dc:relation rdf:resource="https://id.rijksmuseum.nl/20067137" />
                <dc:subject rdf:resource="https://id.rijksmuseum.nl/221357" />
                <dc:subject rdf:resource="https://id.rijksmuseum.nl/221358" />
                <dc:subject rdf:resource="https://id.rijksmuseum.nl/221359" />
                <dc:subject rdf:resource="https://id.rijksmuseum.nl/2307417" />
                <dc:title xml:lang="en">Interieur van de Sint-Bavokerk in Haarlem</dc:title>
                <dc:title xml:lang="en">Interior of the Church of St Bavo in Haarlem</dc:title>
                <dc:title xml:lang="nl">Interieur van de Sint-Bavokerk in Haarlem</dc:title>
                <dc:title xml:lang="nl">Interior of the Church of St Bavo in Haarlem</dc:title>
                <dc:type rdf:resource="https://id.rijksmuseum.nl/2208" />
                <ns5:created xml:lang="en">1636-04-15</ns5:created>
                <ns5:created xml:lang="nl">1636-04-15</ns5:created>
                <ns5:extent xml:lang="en">outer size: depth 7 cm (support incl. frame)</ns5:extent>
                <ns5:extent xml:lang="en">support: height 93.7 cm x width 55.2 cm</ns5:extent>
                <ns5:extent xml:lang="nl">buitenmaat: diepte 7 cm (drager incl. SK-L-1306)</ns5:extent>
                <ns5:extent xml:lang="nl">drager: hoogte 93,7 cm x breedte 55,2 cm</ns5:extent>
                <ns5:isPartOf rdf:resource="https://id.rijksmuseum.nl/260212" />
                <ns5:isPartOf rdf:resource="https://id.rijksmuseum.nl/260214" />
                <ns5:isPartOf rdf:resource="https://id.rijksmuseum.nl/260239" />
                <ns5:isPartOf rdf:resource="https://id.rijksmuseum.nl/260251" />
                <ns5:isPartOf rdf:resource="https://id.rijksmuseum.nl/261208" />
                <ns5:isPartOf rdf:resource="https://id.rijksmuseum.nl/26121" />
                <ns5:isReferencedBy rdf:resource="https://id.rijksmuseum.nl/301100494" />
                <ns5:isReferencedBy rdf:resource="https://id.rijksmuseum.nl/301113606" />
                <ns5:isReferencedBy rdf:resource="https://id.rijksmuseum.nl/30112160" />
                <ns5:isReferencedBy rdf:resource="https://id.rijksmuseum.nl/301218758" />
                <ns5:isReferencedBy rdf:resource="https://id.rijksmuseum.nl/30198970" />
                <ns5:medium rdf:resource="https://id.rijksmuseum.nl/220116" />
                <ns5:medium rdf:resource="https://id.rijksmuseum.nl/2209" />
                <ns5:provenance xml:lang="en">...; ? purchased by the museum from the art dealer P.C. Huybrechts, The Hague, 20 June 1803;{Moes/Van Biema 1909, p. 164, no. 270, with an incorrect inv. no.} ? or, fl. 700, to the museum, with _&lt;em&gt;Interior of the Sint-Bavokerk in Haarlem&lt;/em&gt;_ by Isaac van Nickelen (SK-A-360; at the time listed as Saenredam), 1806;{Note RMA.} on loan to the Frans Hals Museum, Haarlem, 1925-59</ns5:provenance>
                <ns3:currentLocation rdf:resource="https://id.rijksmuseum.nl/2301886" />
                <ns3:type>IMAGE</ns3:type>
              </ns3:ProvidedCHO>
            </ns3:aggregatedCHO>
            <ns3:object>
              <ns3:WebResource rdf:about="https://iiif.micr.io/DVZRG/full/max/0/default.jpg">
                <ns6:has_service rdf:resource="https://iiif.micr.io/DVZRG" />
              </ns3:WebResource>
            </ns3:object>
            <ns3:provider rdf:resource="https://id.rijksmuseum.nl/2109266" />
            <ns3:rights rdf:resource="http://creativecommons.org/publicdomain/mark/1.0/" />
            <ns3:dataProvider>
              <ns3:Agent rdf:about="https://id.rijksmuseum.nl/2109266">
                <ns7:prefLabel xml:lang="en">Rijksmuseum Amsterdam</ns7:prefLabel>
                <ns7:prefLabel xml:lang="nl">Rijksmuseum Amsterdam</ns7:prefLabel>
              </ns3:Agent>
            </ns3:dataProvider>
            <ns3:isShownBy rdf:resource="https://iiif.micr.io/DVZRG/full/max/0/default.jpg" />
            <ns3:isShownAt>
              <ns3:WebResource rdf:about="https://www.rijksmuseum.nl/nl/collectie/object/SK-A-359--3f4dc96d988ead2f72f49799e77bb332">
                <dc:format>text/html</dc:format>
                <dc:language>nl</dc:language>
                <dc:type rdf:resource="http://purl.org/dc/dcmitype/InteractiveResource" />
              </ns3:WebResource>
            </ns3:isShownAt>
          </ns2:Aggregation>
          <rdf:Description rdf:about="https://id.rijksmuseum.nl/260212">
            <ns7:prefLabel xml:lang="en">RijksXL</ns7:prefLabel>
            <ns7:prefLabel xml:lang="nl">RijksXL</ns7:prefLabel>
          </rdf:Description>
          <rdf:Description rdf:about="https://id.rijksmuseum.nl/260214">
            <ns7:prefLabel xml:lang="en">Top 1000</ns7:prefLabel>
            <ns7:prefLabel xml:lang="nl">Top 1000</ns7:prefLabel>
          </rdf:Description>
          <rdf:Description rdf:about="https://id.rijksmuseum.nl/260239">
            <ns7:prefLabel xml:lang="nl">Entire Public Domain Set</ns7:prefLabel>
          </rdf:Description>
          <rdf:Description rdf:about="https://id.rijksmuseum.nl/260251">
            <ns7:prefLabel xml:lang="en">All published objects</ns7:prefLabel>
            <ns7:prefLabel xml:lang="nl">Alle gepubliceerde objecten</ns7:prefLabel>
          </rdf:Description>
          <rdf:Description rdf:about="https://id.rijksmuseum.nl/261208">
            <ns7:prefLabel xml:lang="en">paintings</ns7:prefLabel>
            <ns7:prefLabel xml:lang="nl">schilderijen</ns7:prefLabel>
          </rdf:Description>
          <rdf:Description rdf:about="https://id.rijksmuseum.nl/26121">
            <ns7:prefLabel xml:lang="en">Dutch Paintings of the Seventeenth Century in the Rijksmuseum</ns7:prefLabel>
            <ns7:prefLabel xml:lang="nl">Dutch Paintings of the Seventeenth Century in the Rijksmuseum</ns7:prefLabel>
          </rdf:Description>
          <ns7:Concept rdf:about="https://id.rijksmuseum.nl/220116">
            <ns7:prefLabel xml:lang="en">panel</ns7:prefLabel>
            <ns7:prefLabel xml:lang="nl">paneel</ns7:prefLabel>
          </ns7:Concept>
          <ns7:Concept rdf:about="https://id.rijksmuseum.nl/2208">
            <ns7:prefLabel xml:lang="en">painting</ns7:prefLabel>
            <ns7:prefLabel xml:lang="nl">schilderij</ns7:prefLabel>
          </ns7:Concept>
          <ns7:Concept rdf:about="https://id.rijksmuseum.nl/2209">
            <ns7:prefLabel xml:lang="en">oil paint (paint)</ns7:prefLabel>
            <ns7:prefLabel xml:lang="nl">olieverf</ns7:prefLabel>
          </ns7:Concept>
          <ns7:Concept rdf:about="https://id.rijksmuseum.nl/221357">
            <ns8:sameAs rdf:resource="https://iconclass.org/73E12" />
            <ns7:altLabel>73E12</ns7:altLabel>
            <ns7:prefLabel xml:lang="en">Christ, usually holding a banner, arises from the grave; often combined with sleeping and/or frightened soldiers</ns7:prefLabel>
          </ns7:Concept>
          <ns7:Concept rdf:about="https://id.rijksmuseum.nl/221358">
            <ns8:sameAs rdf:resource="https://iconclass.org/48C73341" />
            <ns7:altLabel>48C73341</ns7:altLabel>
            <ns7:prefLabel xml:lang="en">church organ</ns7:prefLabel>
          </ns7:Concept>
          <ns7:Concept rdf:about="https://id.rijksmuseum.nl/221359">
            <ns8:sameAs rdf:resource="https://iconclass.org/11Q7131" />
            <ns7:altLabel>11Q7131</ns7:altLabel>
            <ns7:prefLabel xml:lang="en">parts of church interior</ns7:prefLabel>
          </ns7:Concept>
          <ns6:Service rdf:about="https://iiif.micr.io/DVZRG">
            <ns5:conformsTo rdf:resource="http://iiif.io/api/image" />
          </ns6:Service>
          <ns3:Agent rdf:about="https://id.rijksmuseum.nl/2101346">
            <ns8:sameAs rdf:resource="http://viaf.org/viaf/9881086" />
            <ns8:sameAs rdf:resource="http://vocab.getty.edu/ulan/500115526" />
            <ns8:sameAs rdf:resource="http://www.wikidata.org/entity/Q433804" />
            <ns8:sameAs rdf:resource="https://rkd.nl/artists/69237" />
            <ns9:dateOfBirth xml:lang="nl">1597-06-09</ns9:dateOfBirth>
            <ns9:dateOfDeath xml:lang="nl">1665-05</ns9:dateOfDeath>
            <ns9:placeOfBirth>
              <ns3:Place rdf:about="https://id.rijksmuseum.nl/2301630">
                <ns7:prefLabel xml:lang="en">Assendelft</ns7:prefLabel>
                <ns7:prefLabel xml:lang="nl">Assendelft</ns7:prefLabel>
              </ns3:Place>
            </ns9:placeOfBirth>
            <ns9:placeOfDeath>
              <ns3:Place rdf:about="https://id.rijksmuseum.nl/230134">
                <ns7:prefLabel xml:lang="en">Haarlem</ns7:prefLabel>
                <ns7:prefLabel xml:lang="nl">Haarlem</ns7:prefLabel>
              </ns3:Place>
            </ns9:placeOfDeath>
            <ns9:professionOrOccupation>
              <ns7:Concept rdf:about="https://id.rijksmuseum.nl/2202217">
                <ns7:prefLabel xml:lang="en">painter</ns7:prefLabel>
                <ns7:prefLabel xml:lang="nl">schilder</ns7:prefLabel>
              </ns7:Concept>
            </ns9:professionOrOccupation>
            <ns9:professionOrOccupation>
              <ns7:Concept rdf:about="https://id.rijksmuseum.nl/2202348">
                <ns7:prefLabel xml:lang="en">printmaker</ns7:prefLabel>
                <ns7:prefLabel xml:lang="nl">prentmaker</ns7:prefLabel>
              </ns7:Concept>
            </ns9:professionOrOccupation>
            <ns9:professionOrOccupation>
              <ns7:Concept rdf:about="https://id.rijksmuseum.nl/2202371">
                <ns7:prefLabel xml:lang="en">draftsman (artist)</ns7:prefLabel>
                <ns7:prefLabel xml:lang="nl">tekenaar</ns7:prefLabel>
              </ns7:Concept>
            </ns9:professionOrOccupation>
            <ns7:altLabel xml:lang="en">Saenredam, Pieter Jansz</ns7:altLabel>
            <ns7:altLabel xml:lang="nl">Pieter Jansz. Sanredam</ns7:altLabel>
            <ns7:altLabel xml:lang="nl">Pieter Jansz. Zaenredam</ns7:altLabel>
            <ns7:altLabel xml:lang="nl">Pieter Saenredam</ns7:altLabel>
            <ns7:altLabel xml:lang="nl">Pieter Zaenredam</ns7:altLabel>
            <ns7:altLabel xml:lang="nl">Saenredam, Pieter Jansz.</ns7:altLabel>
            <ns7:altLabel xml:lang="nl">Saenredam, Pieter</ns7:altLabel>
            <ns7:altLabel xml:lang="nl">Sanredam, Pieter Jansz.</ns7:altLabel>
            <ns7:altLabel xml:lang="nl">Zaenredam, Pieter Jansz.</ns7:altLabel>
            <ns7:altLabel xml:lang="nl">Zaenredam, Pieter</ns7:altLabel>
            <ns7:prefLabel xml:lang="en">Pieter Jansz Saenredam</ns7:prefLabel>
            <ns7:prefLabel xml:lang="nl">Pieter Jansz. Saenredam</ns7:prefLabel>
          </ns3:Agent>
          <ns3:Place rdf:about="https://id.rijksmuseum.nl/2301886">
            <ns7:prefLabel>Rijksmuseum</ns7:prefLabel>
          </ns3:Place>
          <ns3:Place rdf:about="https://id.rijksmuseum.nl/2307417">
            <ns8:sameAs rdf:resource="http://www.wikidata.org/entity/Q1545193" />
            <ns8:sameAs rdf:resource="https://sws.geonames.org/6951282/" />
            <ns7:prefLabel xml:lang="nl">Sint-Bavokerk (Haarlem)</ns7:prefLabel>
          </ns3:Place>
        </rdf:RDF>
      </ns0:metadata>
    </ns0:record>
    