<ns0:record xmlns:dc="http://purl.org/dc/elements/1.1/" xmlns:ns0="http://www.openarchives.org/OAI/2.0/" xmlns:ns2="http://www.openarchives.org/ore/terms/" xmlns:ns3="http://www.europeana.eu/schemas/edm/" xmlns:ns5="http://purl.org/dc/terms/" xmlns:ns6="http://rdfs.org/sioc/services#" xmlns:ns7="http://www.w3.org/2004/02/skos/core#" xmlns:ns8="http://www.w3.org/2002/07/owl#" xmlns:ns9="http://rdvocab.info/ElementsGr2/" xmlns:rdf="http://www.w3.org/1999/02/22-rdf-syntax-ns#">
      <ns0:header>
        <ns0:identifier>https://id.rijksmuseum.nl/20025955</ns0:identifier>
        <ns0:datestamp>2026-06-08T00:15:13Z</ns0:datestamp>
        <ns0:setSpec>260214</ns0:setSpec>
        <ns0:setSpec>260239</ns0:setSpec>
        <ns0:setSpec>261208</ns0:setSpec>
        <ns0:setSpec>26121</ns0:setSpec>
        <ns0:setSpec>260251</ns0:setSpec>
      </ns0:header>
      <ns0:metadata>
        <rdf:RDF>
          <ns2:Aggregation rdf:about="https://id.rijksmuseum.nl/20025955#aggregation">
            <ns3:aggregatedCHO>
              <ns3:ProvidedCHO rdf:about="https://id.rijksmuseum.nl/20025955">
                <dc:creator rdf:resource="https://id.rijksmuseum.nl/2101216" />
                <dc:description xml:lang="nl">De vrolijke boer. Een lachende man met een aardewerken kruik in de handen.</dc:description>
                <dc:identifier>SK-A-302</dc:identifier>
                <dc:subject rdf:resource="https://id.rijksmuseum.nl/221247" />
                <dc:subject rdf:resource="https://id.rijksmuseum.nl/221249" />
                <dc:subject rdf:resource="https://id.rijksmuseum.nl/221254" />
                <dc:title xml:lang="en">The Merry Peasant</dc:title>
                <dc:title xml:lang="nl">De vrolijke boer</dc:title>
                <dc:type rdf:resource="https://id.rijksmuseum.nl/2208" />
                <ns5:created xml:lang="en">c. 1646</ns5:created>
                <ns5:created xml:lang="nl">ca. 1646</ns5:created>
                <ns5:extent xml:lang="en">outer size: height 21.6 cm x width 19.1 cm x depth 1.8 cm (support incl. frame)</ns5:extent>
                <ns5:extent xml:lang="en">support: height 16.4 cm x width 13.9 cm</ns5:extent>
                <ns5:extent xml:lang="nl">buitenmaat: hoogte 21,6 cm x breedte 19,1 cm x diepte 1,8 cm (incl. lijst SK-L-6070)</ns5:extent>
                <ns5:extent xml:lang="nl">drager: hoogte 16,4 cm x breedte 13,9 cm</ns5:extent>
                <ns5:isPartOf rdf:resource="https://id.rijksmuseum.nl/260214" />
                <ns5:isPartOf rdf:resource="https://id.rijksmuseum.nl/260239" />
                <ns5:isPartOf rdf:resource="https://id.rijksmuseum.nl/260251" />
                <ns5:isPartOf rdf:resource="https://id.rijksmuseum.nl/261208" />
                <ns5:isPartOf rdf:resource="https://id.rijksmuseum.nl/26121" />
                <ns5:medium rdf:resource="https://id.rijksmuseum.nl/220116" />
                <ns5:medium rdf:resource="https://id.rijksmuseum.nl/2209" />
                <ns5:provenance xml:lang="en">…; from G. van der Hooft, fl. 31.10, to Gerrit van der Pot (1732-1807), Lord of Groeneveld, Rotterdam, 1782;{_&lt;em&gt;Journaal&lt;/em&gt;_ Pot van Groeneveld, no. 145: ‘Een vroolijke boer met een kan. Van G. van der Hooft in 1782 gekogt voor f 31.10’. See T. Zeedijk, ‘“Tot Voordeel en Genoegen”: De schilderijenverzameling van Gerrit van der Pot van Groenevelt’, _&lt;em&gt;Bulletin van het Rijksmuseum&lt;/em&gt;_ 55 (2007), pp. 128-207, esp. p. 187, no. 145.} his sale, Rotterdam (Gebr. Van Ryp), 6 June 1808 _&lt;em&gt;sqq.&lt;/em&gt;_, no. 98, as Isack van Ostade (‘Hoog 6¼, en breed 5¼ duim [16 x 13.5 cm]. Pnl. Een lagchenden Boer, eene aarden kan in de handen houdende. […]’), fl. 36, to J.M. Jorissen, for the museum{Provenance reconstructed in T. Zeedijk, ‘“Tot Voordeel en Genoegen”: De schilderijenverzameling van Gerrit van der Pot van Groenevelt’, _&lt;em&gt;Bulletin van het Rijksmuseum&lt;/em&gt;_ 55 (2007), pp. 128-207, esp. p. 187, no. 145.}</ns5:provenance>
                <ns3:type>IMAGE</ns3:type>
              </ns3:ProvidedCHO>
            </ns3:aggregatedCHO>
            <ns3:object>
              <ns3:WebResource rdf:about="https://iiif.micr.io/gsZuA/full/max/0/default.jpg">
                <ns6:has_service rdf:resource="https://iiif.micr.io/gsZuA" />
              </ns3:WebResource>
            </ns3:object>
            <ns3:provider rdf:resource="https://id.rijksmuseum.nl/2109266" />
            <ns3:rights rdf:resource="http://creativecommons.org/publicdomain/mark/1.0/" />
            <ns3:dataProvider>
              <ns3:Agent rdf:about="https://id.rijksmuseum.nl/2109266">
                <ns7:prefLabel xml:lang="en">Rijksmuseum Amsterdam</ns7:prefLabel>
                <ns7:prefLabel xml:lang="nl">Rijksmuseum Amsterdam</ns7:prefLabel>
              </ns3:Agent>
            </ns3:dataProvider>
            <ns3:isShownBy rdf:resource="https://iiif.micr.io/gsZuA/full/max/0/default.jpg" />
            <ns3:isShownAt>
              <ns3:WebResource rdf:about="https://www.rijksmuseum.nl/nl/collectie/object/SK-A-302--411aa482a7835a919efae3b9fa5766b8">
                <dc:format>text/html</dc:format>
                <dc:language>nl</dc:language>
                <dc:type rdf:resource="http://purl.org/dc/dcmitype/InteractiveResource" />
              </ns3:WebResource>
            </ns3:isShownAt>
          </ns2:Aggregation>
          <rdf:Description rdf:about="https://id.rijksmuseum.nl/260214">
            <ns7:prefLabel xml:lang="en">Top 1000</ns7:prefLabel>
            <ns7:prefLabel xml:lang="nl">Top 1000</ns7:prefLabel>
          </rdf:Description>
          <rdf:Description rdf:about="https://id.rijksmuseum.nl/260239">
            <ns7:prefLabel xml:lang="nl">Entire Public Domain Set</ns7:prefLabel>
          </rdf:Description>
          <rdf:Description rdf:about="https://id.rijksmuseum.nl/260251">
            <ns7:prefLabel xml:lang="en">All published objects</ns7:prefLabel>
            <ns7:prefLabel xml:lang="nl">Alle gepubliceerde objecten</ns7:prefLabel>
          </rdf:Description>
          <rdf:Description rdf:about="https://id.rijksmuseum.nl/261208">
            <ns7:prefLabel xml:lang="en">paintings</ns7:prefLabel>
            <ns7:prefLabel xml:lang="nl">schilderijen</ns7:prefLabel>
          </rdf:Description>
          <rdf:Description rdf:about="https://id.rijksmuseum.nl/26121">
            <ns7:prefLabel xml:lang="en">Dutch Paintings of the Seventeenth Century in the Rijksmuseum</ns7:prefLabel>
            <ns7:prefLabel xml:lang="nl">Dutch Paintings of the Seventeenth Century in the Rijksmuseum</ns7:prefLabel>
          </rdf:Description>
          <ns7:Concept rdf:about="https://id.rijksmuseum.nl/220116">
            <ns7:prefLabel xml:lang="en">panel</ns7:prefLabel>
            <ns7:prefLabel xml:lang="nl">paneel</ns7:prefLabel>
          </ns7:Concept>
          <ns7:Concept rdf:about="https://id.rijksmuseum.nl/2208">
            <ns7:prefLabel xml:lang="en">painting</ns7:prefLabel>
            <ns7:prefLabel xml:lang="nl">schilderij</ns7:prefLabel>
          </ns7:Concept>
          <ns7:Concept rdf:about="https://id.rijksmuseum.nl/2209">
            <ns7:prefLabel xml:lang="en">oil paint (paint)</ns7:prefLabel>
            <ns7:prefLabel xml:lang="nl">olieverf</ns7:prefLabel>
          </ns7:Concept>
          <ns7:Concept rdf:about="https://id.rijksmuseum.nl/221247">
            <ns8:sameAs rdf:resource="https://iconclass.org/41C326" />
            <ns7:altLabel>41C326</ns7:altLabel>
            <ns7:prefLabel xml:lang="en">jar, jug (used as drinking-vessel)</ns7:prefLabel>
          </ns7:Concept>
          <ns7:Concept rdf:about="https://id.rijksmuseum.nl/221249">
            <ns8:sameAs rdf:resource="https://iconclass.org/46A14" />
            <ns7:altLabel>46A14</ns7:altLabel>
            <ns7:prefLabel xml:lang="en">farmers</ns7:prefLabel>
          </ns7:Concept>
          <ns7:Concept rdf:about="https://id.rijksmuseum.nl/221254">
            <ns8:sameAs rdf:resource="https://iconclass.org/31B62321" />
            <ns7:altLabel>31B62321</ns7:altLabel>
            <ns7:prefLabel xml:lang="en">laughing</ns7:prefLabel>
          </ns7:Concept>
          <ns6:Service rdf:about="https://iiif.micr.io/gsZuA">
            <ns5:conformsTo rdf:resource="http://iiif.io/api/image" />
          </ns6:Service>
          <ns3:Agent rdf:about="https://id.rijksmuseum.nl/2101216">
            <ns8:sameAs rdf:resource="http://viaf.org/viaf/24760273" />
            <ns8:sameAs rdf:resource="http://vocab.getty.edu/ulan/500021654" />
            <ns8:sameAs rdf:resource="http://www.wikidata.org/entity/Q352438" />
            <ns8:sameAs rdf:resource="https://rkd.nl/artists/61082" />
            <ns9:dateOfBirth xml:lang="nl">1610-12 - 1610-12-19</ns9:dateOfBirth>
            <ns9:dateOfDeath xml:lang="nl">1685-04-28</ns9:dateOfDeath>
            <ns9:placeOfBirth rdf:resource="https://id.rijksmuseum.nl/230134" />
            <ns9:placeOfDeath>
              <ns3:Place rdf:about="https://id.rijksmuseum.nl/230134">
                <ns7:prefLabel xml:lang="en">Haarlem</ns7:prefLabel>
                <ns7:prefLabel xml:lang="nl">Haarlem</ns7:prefLabel>
              </ns3:Place>
            </ns9:placeOfDeath>
            <ns9:professionOrOccupation>
              <ns7:Concept rdf:about="https://id.rijksmuseum.nl/2202217">
                <ns7:prefLabel xml:lang="en">painter</ns7:prefLabel>
                <ns7:prefLabel xml:lang="nl">schilder</ns7:prefLabel>
              </ns7:Concept>
            </ns9:professionOrOccupation>
            <ns9:professionOrOccupation>
              <ns7:Concept rdf:about="https://id.rijksmuseum.nl/2202348">
                <ns7:prefLabel xml:lang="en">printmaker</ns7:prefLabel>
                <ns7:prefLabel xml:lang="nl">prentmaker</ns7:prefLabel>
              </ns7:Concept>
            </ns9:professionOrOccupation>
            <ns9:professionOrOccupation>
              <ns7:Concept rdf:about="https://id.rijksmuseum.nl/2202371">
                <ns7:prefLabel xml:lang="en">draftsman (artist)</ns7:prefLabel>
                <ns7:prefLabel xml:lang="nl">tekenaar</ns7:prefLabel>
              </ns7:Concept>
            </ns9:professionOrOccupation>
            <ns7:altLabel xml:lang="en">Ostade, Adriaen van</ns7:altLabel>
            <ns7:altLabel xml:lang="nl">Adriaan van Ostade</ns7:altLabel>
            <ns7:altLabel xml:lang="nl">Adriaen Jansz. van Ostade</ns7:altLabel>
            <ns7:altLabel xml:lang="nl">Ostade, Adriaan van</ns7:altLabel>
            <ns7:altLabel xml:lang="nl">Ostade, Adriaen Jansz. van</ns7:altLabel>
            <ns7:altLabel xml:lang="nl">Ostade, Adriaen van</ns7:altLabel>
            <ns7:prefLabel xml:lang="en">Adriaen van Ostade</ns7:prefLabel>
            <ns7:prefLabel xml:lang="nl">Adriaen van Ostade</ns7:prefLabel>
          </ns3:Agent>
        </rdf:RDF>
      </ns0:metadata>
    </ns0:record>
    