<ns0:record xmlns:dc="http://purl.org/dc/elements/1.1/" xmlns:ns0="http://www.openarchives.org/OAI/2.0/" xmlns:ns10="http://rdvocab.info/ElementsGr2/" xmlns:ns2="http://www.openarchives.org/ore/terms/" xmlns:ns3="http://www.europeana.eu/schemas/edm/" xmlns:ns5="http://purl.org/dc/terms/" xmlns:ns6="http://id.loc.gov/vocabulary/relators/" xmlns:ns7="http://rdfs.org/sioc/services#" xmlns:ns8="http://www.w3.org/2004/02/skos/core#" xmlns:ns9="http://www.w3.org/2002/07/owl#" xmlns:rdf="http://www.w3.org/1999/02/22-rdf-syntax-ns#">
      <ns0:header>
        <ns0:identifier>https://id.rijksmuseum.nl/200108464</ns0:identifier>
        <ns0:datestamp>2026-06-08T00:22:24Z</ns0:datestamp>
        <ns0:setSpec>260241</ns0:setSpec>
        <ns0:setSpec>260214</ns0:setSpec>
        <ns0:setSpec>260239</ns0:setSpec>
        <ns0:setSpec>26136</ns0:setSpec>
        <ns0:setSpec>260251</ns0:setSpec>
      </ns0:header>
      <ns0:metadata>
        <rdf:RDF>
          <ns2:Aggregation rdf:about="https://id.rijksmuseum.nl/200108464#aggregation">
            <ns3:aggregatedCHO>
              <ns3:ProvidedCHO rdf:about="https://id.rijksmuseum.nl/200108464">
                <dc:creator rdf:resource="https://id.rijksmuseum.nl/2106343" />
                <dc:description xml:lang="en">According to Liotard, the dauphine was so impressed by Liotard’s pastels, among them La Liseuse, that Liotard was invited to make portraits of almost the entire French royal family. This example, which Liotard kept for himself, is one of the most charming in its simple presentation of the newlywed young princess.</dc:description>
                <dc:description xml:lang="nl">Volgens Liotard was de Dauphine zo onder de indruk van zijn pastels, waaronder La Liseuse, dat Liotard uitgenodigd werd om portretten te maken van bijna de hele Franse koninklijke familie. Bij dit werk – dat hij voor zichzelf hield – gaf hij de pasgetrouwde prinses zeer charmant eenvoudig weer.</dc:description>
                <dc:identifier>SK-A-238</dc:identifier>
                <dc:subject rdf:resource="https://id.rijksmuseum.nl/21067034" />
                <dc:subject rdf:resource="https://id.rijksmuseum.nl/221173" />
                <dc:title xml:lang="en">Maria Josepha of Saxony, Dauphine of France</dc:title>
                <dc:title xml:lang="en">Maria Josepha van Saksen, Dauphine van Frankrijk</dc:title>
                <dc:title xml:lang="nl">Maria Josepha of Saxony, Dauphine of France</dc:title>
                <dc:title xml:lang="nl">Maria Josepha van Saksen, Dauphine van Frankrijk</dc:title>
                <dc:type rdf:resource="https://id.rijksmuseum.nl/220363" />
                <dc:type rdf:resource="https://id.rijksmuseum.nl/220461" />
                <ns5:created xml:lang="en">1749</ns5:created>
                <ns5:created xml:lang="nl">1749</ns5:created>
                <ns5:extent xml:lang="en">height 113.6 cm x width 88.8 cm x thickness 6.3 cm</ns5:extent>
                <ns5:extent xml:lang="en">height 41 cm x width 32.5 cm</ns5:extent>
                <ns5:extent xml:lang="en">weight 2.4 kg</ns5:extent>
                <ns5:extent xml:lang="nl">buitenmaat: hoogte 113,6 cm x breedte 88,8 cm x dikte 6,3 cm</ns5:extent>
                <ns5:extent xml:lang="nl">drager: hoogte 41 cm x breedte 32,5 cm</ns5:extent>
                <ns5:extent xml:lang="nl">geheel: gewicht (eigenschap) 2,4 kg (inclusief lijst en 2mm glas)</ns5:extent>
                <ns5:isPartOf rdf:resource="https://id.rijksmuseum.nl/260214" />
                <ns5:isPartOf rdf:resource="https://id.rijksmuseum.nl/260239" />
                <ns5:isPartOf rdf:resource="https://id.rijksmuseum.nl/260241" />
                <ns5:isPartOf rdf:resource="https://id.rijksmuseum.nl/260251" />
                <ns5:isPartOf rdf:resource="https://id.rijksmuseum.nl/26136" />
                <ns5:isReferencedBy rdf:resource="https://id.rijksmuseum.nl/301243940" />
                <ns5:isReferencedBy rdf:resource="https://id.rijksmuseum.nl/301251001" />
                <ns5:isReferencedBy rdf:resource="https://id.rijksmuseum.nl/30186475" />
                <ns5:isReferencedBy>Documentatiemap Schilderijen: aantekeningen R. van Luttervelt (voor 1963).</ns5:isReferencedBy>
                <ns6:spn xml:lang="en">Bequeathed by Miss Marie-Anne Liotard, Amsterdam</ns6:spn>
                <ns6:spn xml:lang="nl">Legaat van mejuffrouw Marie-Anne Liotard, Amsterdam</ns6:spn>
                <ns3:type>IMAGE</ns3:type>
              </ns3:ProvidedCHO>
            </ns3:aggregatedCHO>
            <ns3:object>
              <ns3:WebResource rdf:about="https://iiif.micr.io/cmAEt/full/max/0/default.jpg">
                <ns7:has_service rdf:resource="https://iiif.micr.io/cmAEt" />
              </ns3:WebResource>
            </ns3:object>
            <ns3:provider rdf:resource="https://id.rijksmuseum.nl/2109266" />
            <ns3:rights rdf:resource="http://creativecommons.org/publicdomain/mark/1.0/" />
            <ns3:dataProvider>
              <ns3:Agent rdf:about="https://id.rijksmuseum.nl/2109266">
                <ns8:prefLabel xml:lang="en">Rijksmuseum Amsterdam</ns8:prefLabel>
                <ns8:prefLabel xml:lang="nl">Rijksmuseum Amsterdam</ns8:prefLabel>
              </ns3:Agent>
            </ns3:dataProvider>
            <ns3:isShownBy rdf:resource="https://iiif.micr.io/cmAEt/full/max/0/default.jpg" />
            <ns3:isShownAt>
              <ns3:WebResource rdf:about="https://www.rijksmuseum.nl/nl/collectie/object/SK-A-238--fe7c53a10961fac090787af45d5e633b">
                <dc:format>text/html</dc:format>
                <dc:language>nl</dc:language>
                <dc:type rdf:resource="http://purl.org/dc/dcmitype/InteractiveResource" />
              </ns3:WebResource>
            </ns3:isShownAt>
          </ns2:Aggregation>
          <rdf:Description rdf:about="https://id.rijksmuseum.nl/260214">
            <ns8:prefLabel xml:lang="en">Top 1000</ns8:prefLabel>
            <ns8:prefLabel xml:lang="nl">Top 1000</ns8:prefLabel>
          </rdf:Description>
          <rdf:Description rdf:about="https://id.rijksmuseum.nl/260239">
            <ns8:prefLabel xml:lang="nl">Entire Public Domain Set</ns8:prefLabel>
          </rdf:Description>
          <rdf:Description rdf:about="https://id.rijksmuseum.nl/260241">
            <ns8:prefLabel xml:lang="en">biografic</ns8:prefLabel>
            <ns8:prefLabel xml:lang="nl">biografisch</ns8:prefLabel>
          </rdf:Description>
          <rdf:Description rdf:about="https://id.rijksmuseum.nl/260251">
            <ns8:prefLabel xml:lang="en">All published objects</ns8:prefLabel>
            <ns8:prefLabel xml:lang="nl">Alle gepubliceerde objecten</ns8:prefLabel>
          </rdf:Description>
          <rdf:Description rdf:about="https://id.rijksmuseum.nl/26136">
            <ns8:prefLabel xml:lang="nl">pastels</ns8:prefLabel>
          </rdf:Description>
          <ns8:Concept rdf:about="https://id.rijksmuseum.nl/220363">
            <ns8:prefLabel xml:lang="en">drawing</ns8:prefLabel>
            <ns8:prefLabel xml:lang="nl">tekening</ns8:prefLabel>
          </ns8:Concept>
          <ns8:Concept rdf:about="https://id.rijksmuseum.nl/220461">
            <ns8:prefLabel xml:lang="en">pastel</ns8:prefLabel>
            <ns8:prefLabel xml:lang="nl">pastel</ns8:prefLabel>
          </ns8:Concept>
          <ns8:Concept rdf:about="https://id.rijksmuseum.nl/221173">
            <ns9:sameAs rdf:resource="https://iconclass.org/61BB2" />
            <ns8:altLabel>61BB2</ns8:altLabel>
            <ns8:prefLabel xml:lang="en">historical persons - BB - woman</ns8:prefLabel>
          </ns8:Concept>
          <ns7:Service rdf:about="https://iiif.micr.io/cmAEt">
            <ns5:conformsTo rdf:resource="http://iiif.io/api/image" />
          </ns7:Service>
          <ns3:Agent rdf:about="https://id.rijksmuseum.nl/2106343">
            <ns9:sameAs rdf:resource="http://viaf.org/viaf/61675695" />
            <ns9:sameAs rdf:resource="http://vocab.getty.edu/ulan/500003329" />
            <ns9:sameAs rdf:resource="http://www.wikidata.org/entity/Q123757" />
            <ns9:sameAs rdf:resource="https://rkd.nl/artists/50314" />
            <ns10:dateOfBirth xml:lang="nl">1702-12-22</ns10:dateOfBirth>
            <ns10:dateOfDeath xml:lang="nl">1789-06-12</ns10:dateOfDeath>
            <ns10:placeOfBirth rdf:resource="https://id.rijksmuseum.nl/230483" />
            <ns10:placeOfDeath>
              <ns3:Place rdf:about="https://id.rijksmuseum.nl/230483">
                <ns8:prefLabel xml:lang="nl">Genève</ns8:prefLabel>
              </ns3:Place>
            </ns10:placeOfDeath>
            <ns10:professionOrOccupation>
              <ns8:Concept rdf:about="https://id.rijksmuseum.nl/2202217">
                <ns8:prefLabel xml:lang="en">painter</ns8:prefLabel>
                <ns8:prefLabel xml:lang="nl">schilder</ns8:prefLabel>
              </ns8:Concept>
            </ns10:professionOrOccupation>
            <ns10:professionOrOccupation>
              <ns8:Concept rdf:about="https://id.rijksmuseum.nl/2202348">
                <ns8:prefLabel xml:lang="en">printmaker</ns8:prefLabel>
                <ns8:prefLabel xml:lang="nl">prentmaker</ns8:prefLabel>
              </ns8:Concept>
            </ns10:professionOrOccupation>
            <ns8:altLabel xml:lang="en">Liotard, Jean-Etienne</ns8:altLabel>
            <ns8:altLabel xml:lang="nl">Liotard, Jean-Etienne</ns8:altLabel>
            <ns8:altLabel xml:lang="nl">Liotard</ns8:altLabel>
            <ns8:prefLabel xml:lang="en">Jean-Etienne Liotard</ns8:prefLabel>
            <ns8:prefLabel xml:lang="nl">Jean-Etienne Liotard</ns8:prefLabel>
          </ns3:Agent>
          <ns3:Agent rdf:about="https://id.rijksmuseum.nl/21067034">
            <ns9:sameAs rdf:resource="http://viaf.org/viaf/61817959" />
            <ns9:sameAs rdf:resource="http://www.wikidata.org/entity/Q163043" />
            <ns10:dateOfBirth xml:lang="nl">1731-11-04</ns10:dateOfBirth>
            <ns10:dateOfDeath xml:lang="nl">1767-03-13</ns10:dateOfDeath>
            <ns10:placeOfBirth rdf:resource="https://id.rijksmuseum.nl/230723" />
            <ns10:placeOfDeath>
              <ns3:Place rdf:about="https://id.rijksmuseum.nl/230215">
                <ns8:prefLabel xml:lang="en">Paris</ns8:prefLabel>
                <ns8:prefLabel xml:lang="nl">Parijs</ns8:prefLabel>
              </ns3:Place>
            </ns10:placeOfDeath>
            <ns8:prefLabel xml:lang="en">Maria Josepha Carolina van Saksen</ns8:prefLabel>
            <ns8:prefLabel xml:lang="nl">Maria Josepha Carolina van Saksen</ns8:prefLabel>
          </ns3:Agent>
          <ns3:Place rdf:about="https://id.rijksmuseum.nl/230723">
            <ns8:prefLabel xml:lang="nl">Dresden</ns8:prefLabel>
          </ns3:Place>
        </rdf:RDF>
      </ns0:metadata>
    </ns0:record>
    